[
      {
        "id": 1,
        "company": "Google",
        "image": "https://i.ibb.co/rxDbSSY/google.png",
        "job_description": "Join Google's innovative team to work on cutting-edge projects!",
        "job_responsibilities": "Develop and maintain web applications, collaborate with cross-functional teams.",
        "education": "Bachelor's degree in Computer Science or related field.",
        "experience": "2+ years of relevant experience.",
        "salary": "$120,000 - $150,000 per year",
        "job_title": "Software Engineer",
        "job_type": "Onsite",
        "phone": "+1 (123) 456-7890",
        "email": "careers@google.com",
        "address": "123 Google Way, Mountain View, CA"
      },
      {
        "id": 2,
        "company": "Netflix",
        "image": "https://i.ibb.co/xzNS0hs/netflix.png",
        "job_description": "Join Netflix's content creation team and shape the future of entertainment!",
        "job_responsibilities": "Create original content, collaborate with directors, writers, and actors.",
        "education": "Bachelor's degree in Film Production or related field.",
        "experience": "3+ years of relevant experience.",
        "salary": "$80,000 - $100,000 per year",
        "job_title": "Content Producer",
        "job_type": "Remote",
        "phone": "+1 (234) 567-8901",
        "email": "jobs@netflix.com",
        "address": "456 Stream Street, Los Angeles, CA"
      },
      {
        "id": 3,
        "company": "Tesla",
        "image": "https://i.ibb.co/BZvC7bk/tesla.png",
        "job_description": "Join Tesla's mission to accelerate the world's transition to sustainable energy!",
        "job_responsibilities": "Design and develop electric vehicle systems, perform testing and validation.",
        "education": "Bachelor's degree in Mechanical Engineering or related field.",
        "experience": "5+ years of relevant experience.",
        "salary": "$90,000 - $120,000 per year",
        "job_title": "Mechanical Engineer",
        "job_type": "Onsite",
        "phone": "+1 (345) 678-9012",
        "email": "careers@tesla.com",
        "address": "789 Electric Avenue, Palo Alto, CA"
      },
      {
        "id": 4,
        "company": "Airbnb",
        "image": "https://i.ibb.co/16F7jJR/airbnb.png",
        "job_description": "Join Airbnb and help people belong anywhere in the world!",
        "job_responsibilities": "Manage customer support operations, resolve guest and host issues.",
        "education": "Bachelor's degree in Hospitality Management or related field.",
        "experience": "2+ years of relevant experience.",
        "salary": "$70,000 - $90,000 per year",
        "job_title": "Customer Support Specialist",
        "job_type": "Remote",
        "phone": "+1 (456) 789-0123",
        "email": "careers@airbnb.com",
        "address": "101 Stay Street, San Francisco, CA"
      },
      {
        "id": 5,
        "company": "Netflix",
        "image": "https://i.ibb.co/xzNS0hs/netflix.png",
        "job_description": "Help Netflix create an amazing user experience for viewers worldwide!",
        "job_responsibilities": "Design user interfaces, conduct user research, and iterate on designs.",
        "education": "Bachelor's degree in Interaction Design or related field.",
        "experience": "3+ years of relevant experience.",
        "salary": "$85,000 - $110,000 per year",
        "job_title": "UI/UX Designer",
        "job_type": "Onsite",
        "phone": "+1 (234) 567-8901",
        "email": "jobs@netflix.com",
        "address": "456 Stream Street, Los Angeles, CA"
      },
      {
        "id": 6,
        "company": "Tesla",
        "image": "https://i.ibb.co/BZvC7bk/tesla.png",
        "job_description": "Join Tesla's Autopilot team to revolutionize self-driving technology!",
        "job_responsibilities": "Develop machine learning algorithms, analyze data, and improve autonomy.",
        "education": "Master's degree in Computer Science or related field.",
        "experience": "4+ years of relevant experience.",
        "salary": "$100,000 - $130,000 per year",
        "job_title": "Machine Learning Engineer",
        "job_type": "Onsite",
        "phone": "+1 (345) 678-9012",
        "email": "careers@tesla.com",
        "address": "789 Electric Avenue, Palo Alto, CA"
      }
    ]
  
  